SimpleFileEdit/FileManager.py
SimpleFileEdit/FolderManager.py
SimpleFileEdit/__init__.py
SimpleFileEdit-0.3.0.dist-info/LICENSE
SimpleFileEdit-0.3.0.dist-info/METADATA
SimpleFileEdit-0.3.0.dist-info/WHEEL
SimpleFileEdit-0.3.0.dist-info/top_level.txt
SimpleFileEdit-0.3.0.dist-info/RECORD
