Metadata-Version: 2.1
Name: SimpleFileEdit
Version: 0.3.0
Summary: A tool that makes file and folder managing in python the simplest it can get!
Home-page: https://github.com/BravestCheetah/SimpleFileEdit
Author: BravestCheetah
Author-email: bravestcheetah@gmail.com
Classifier: Programming Language :: Python :: 3
Classifier: License :: OSI Approved :: MIT License
Classifier: Operating System :: OS Independent
Requires-Python: >=3.6
License-File: LICENSE
